test_python_package/__init__.py
test_python_package/example.py
test_python_package_krish/__init__.py
test_python_package_krish/example.py
test_python_package_krish-0.1.1.dist-info/METADATA
test_python_package_krish-0.1.1.dist-info/WHEEL
test_python_package_krish-0.1.1.dist-info/top_level.txt
test_python_package_krish-0.1.1.dist-info/RECORD
